kindlecomicconverter/__init__.py
kindlecomicconverter/comic2ebook.py
kindlecomicconverter/comic2panel.py
kindlecomicconverter/comicarchive.py
kindlecomicconverter/dualmetafix.py
kindlecomicconverter/image.py
kindlecomicconverter/kindle.py
kindlecomicconverter/metadata.py
kindlecomicconverter/pdfjpgextract.py
kindlecomicconverter/shared.py
kindlecomicconverter/startup.py
KindleComicConverter_headless-5.5.2.dist-info/LICENSE.txt
KindleComicConverter_headless-5.5.2.dist-info/METADATA
KindleComicConverter_headless-5.5.2.dist-info/WHEEL
KindleComicConverter_headless-5.5.2.dist-info/entry_points.txt
KindleComicConverter_headless-5.5.2.dist-info/top_level.txt
KindleComicConverter_headless-5.5.2.dist-info/RECORD
